README.rst
setup.cfg
setup.py
djnodb/__init__.py
djnodb/runner.py
djnodb.egg-info/PKG-INFO
djnodb.egg-info/SOURCES.txt
djnodb.egg-info/dependency_links.txt
djnodb.egg-info/requires.txt
djnodb.egg-info/top_level.txt