Metadata-Version: 1.1
Name: djnodb
Version: 0.0.2
Summary: custom django testrunner
Home-page: https://github.com/weeksghost/dj-nodb
Author: Erik Marty
Author-email: erikomarty@yahoo.com
License: Apache
Download-URL: https://github.com/weeksghost/dj-nodb/tarball/0.0.3
Platform: UNKNOWN
Classifier: Environment :: Web Environment
Classifier: Intended Audience :: Developers
Classifier: License :: OSI Approved :: BSD License
Classifier: Operating System :: OS Independent
Classifier: Programming Language :: Python
Classifier: Topic :: Internet :: WWW/HTTP :: Dynamic Content
Classifier: Topic :: Software Development :: Libraries :: Python Modules
